emblaze/__init__.py
emblaze/_version.py
emblaze/datasets.py
emblaze/frame_colors.py
emblaze/neighbors.py
emblaze/recommender.py
emblaze/server.py
emblaze/thumbnails.py
emblaze/utils.py
emblaze/viewer.py
emblaze/data/MNIST.json
emblaze/data/Word Embeddings.json
emblaze/public/favicon.ico
emblaze/public/global.css
emblaze/public/index.html
emblaze/static/style.css
emblaze/static/widget-main.js
emblaze-0.11.0.dist-info/licenses/LICENSE.txt
emblaze-0.11.0.dist-info/METADATA
emblaze-0.11.0.dist-info/WHEEL
emblaze-0.11.0.dist-info/top_level.txt
emblaze-0.11.0.dist-info/RECORD
