Metadata-Version: 2.4
Name: emblaze
Version: 0.11.0
Summary: Interactive widget for embedding comparison
Author-email: Venkatesh Sivaraman <venkats@cmu.edu>
Project-URL: Homepage, https://github.com/cmudig/emblaze
Keywords: AI,machine learning,notebook,jupyter,data science
Classifier: Programming Language :: Python :: 3
Classifier: License :: OSI Approved :: MIT License
Requires-Python: >=3.7
License-File: LICENSE.txt
Requires-Dist: affine>=2.3.0
Requires-Dist: colormath>=3.0.0
Requires-Dist: numpy>=1.19.5
Requires-Dist: pandas>=1.2.0
Requires-Dist: scikit-learn>=0.24.1
Requires-Dist: scipy>=1.6.0
Requires-Dist: pillow>=8.2.0
Requires-Dist: umap-learn>=0.5.1
Requires-Dist: flask>=1.1.2
Requires-Dist: flask-socketio>=5.1.1
Requires-Dist: eventlet>=0.33.0
Requires-Dist: numba>=0.53.1
Requires-Dist: tqdm>=4.61.2
Requires-Dist: ipywidgets
Requires-Dist: anywidget>=0.9.0
Dynamic: license-file
